hepunits/__init__.py
hepunits/_version.py
hepunits/_version.pyi
hepunits/pint.py
hepunits/py.typed
hepunits/constants/__init__.py
hepunits/constants/constants.py
hepunits/units/__init__.py
hepunits/units/prefixes.py
hepunits/units/units.py
hepunits-2.4.4.dist-info/METADATA
hepunits-2.4.4.dist-info/WHEEL
hepunits-2.4.4.dist-info/licenses/LICENSE
hepunits-2.4.4.dist-info/RECORD
