Metadata-Version: 2.4
Name: hepunits
Version: 2.4.4
Summary: Units and constants in the HEP system of units
Project-URL: Homepage, https://github.com/scikit-hep/hepunits
Author-email: Eduardo Rodrigues <eduardo.rodrigues@cern.ch>
Maintainer-email: Scikit-HEP <scikit-hep-admins@googlegroups.com>
License-Expression: BSD-3-Clause
License-File: LICENSE
Keywords: Constants,HEP,HEP system of units,Units
Classifier: Development Status :: 5 - Production/Stable
Classifier: Intended Audience :: Developers
Classifier: Intended Audience :: Science/Research
Classifier: Operating System :: OS Independent
Classifier: Programming Language :: Python
Classifier: Programming Language :: Python :: 3
Classifier: Programming Language :: Python :: 3 :: Only
Classifier: Programming Language :: Python :: 3.9
Classifier: Programming Language :: Python :: 3.10
Classifier: Programming Language :: Python :: 3.11
Classifier: Programming Language :: Python :: 3.12
Classifier: Programming Language :: Python :: 3.13
Classifier: Programming Language :: Python :: 3.14
Classifier: Topic :: Scientific/Engineering
Requires-Python: >=3.9
Provides-Extra: all
Requires-Dist: pint<0.25.1; extra == 'all'
Requires-Dist: pytest-cov>=2.8.0; extra == 'all'
Requires-Dist: pytest>=6; extra == 'all'
Provides-Extra: dev
Requires-Dist: pint<0.25.1; extra == 'dev'
Requires-Dist: pytest-cov>=2.8.0; extra == 'dev'
Requires-Dist: pytest>=6; extra == 'dev'
Provides-Extra: test
Requires-Dist: pint<0.25.1; extra == 'test'
Requires-Dist: pytest-cov>=2.8.0; extra == 'test'
Requires-Dist: pytest>=6; extra == 'test'
